{
  "elements": [
      {
          "type": "ExpansionPanel",
          "caption": "Info zum Modul",
          "items": [
              {
                  "type": "Label",
                  "label": "Dieses Modul ermöglicht, Daten der Luxtronic von verschiedener Wärmepumpen-Hersteller abzufragen."
              },
              {
                  "type": "Label",
                  "label": "Mit der aktuellen Varsion des Moduls ist kein Eingriff in die Steuerung möglich."
              },
              {
                  "type": "Label",
                  "label": "Es muss sichergestellt werden, dass der Port 8888 (ältere Lux) oder 8889 (neuere Lux) nicht durch die Firewall blockiert ist."
              },
              {
                  "type": "Label",
                  "label": "Die Beschreibung und ID's der Variablen ist hier zu finden: https://loxwiki.atlassian.net/wiki/spaces/LOX/pages/1533935933/Java+Webinterface"
              }
          ]
      },
      {
          "type": "GridLayout",
          "columns": 2,
          "items": [
              {
                  "type": "Label",
                  "caption": "IP-Address"
              },
              {
                  "name": "IPAddress",
                  "type": "ValidationTextBox"
              },
              {
                  "type": "Label",
                  "caption": "Port (8888 oder 8889)"
              },
              {
                  "name": "Port",
                  "type": "NumberSpinner"
              },
              {
                  "type": "Label",
                  "caption": "Sekunden"
              },
              {
                  "type": "IntervalBox",
                  "name": "UpdateInterval"
              },
              {
                  "type": "Label",
                  "caption": "Heizung"
              },
              {
                  "type": "CheckBox",
                  "name": "Heizung",
                  "caption": ""
              },
              {
                  "type": "Label",
                  "caption": "Kühlung"
              },
              {
                  "type": "CheckBox",
                  "name": "Kuehlung",
                  "caption": ""
              },
              {
                  "type": "Label",
                  "caption": "Warmwasser"
              },
              {
                  "type": "CheckBox",
                  "name": "Warmwasser",
                  "caption": ""
              }
          ]
      },
      {
          "type": "List",
          "name": "IDListe",
          "caption": "Überwachte ID's",
          "rowCount": 15,
          "add": true,
          "delete": true,
          "sort": {
              "column": "id",
              "direction": "ascending"
          },
          "columns": [
              {
                  "name": "id",
                  "caption": "ID des Wertes",
                  "width": "150",
                  "add": 0,
                  "edit": {
                      "type": "NumberSpinner"
                  }
              }
          ]
      }
  ]
}
